[{"date": "2023-03-01", "hourUtc": 6, "station": "IODESS44", "solarRad": 54.6}, {"date": "2023-03-01", "hourUtc": 9, "station": "IODESS44", "solarRad": 471.5}, {"date": "2023-03-01", "hourUtc": 12, "station": "IODESS44", "solarRad": 412.9}, {"date": "2023-03-01", "hourUtc": 15, "station": "IODESS44", "solarRad": 31.2}, {"date": "2023-03-02", "hourUtc": 6, "station": "IODESS44", "solarRad": 53.7}, {"date": "2023-03-02", "hourUtc": 9, "station": "IODESS44", "solarRad": 588.2}, {"date": "2023-03-02", "hourUtc": 12, "station": "IODESS44", "solarRad": 456.3}, {"date": "2023-03-02", "hourUtc": 15, "station": "IODESS44", "solarRad": 31.6}, {"date": "2023-03-03", "hourUtc": 6, "station": "IODESS44", "solarRad": 63.7}, {"date": "2023-03-03", "hourUtc": 9, "station": "IODESS44", "solarRad": 479.3}, {"date": "2023-03-03", "hourUtc": 12, "station": "IODESS44", "solarRad": 415.6}, {"date": "2023-03-03", "hourUtc": 15, "station": "IODESS44", "solarRad": 31.2}, {"date": "2023-03-04", "hourUtc": 6, "station": "IODESS44", "solarRad": 62.4}, {"date": "2023-03-04", "hourUtc": 9, "station": "IODESS44", "solarRad": 491.9}, {"date": "2023-03-04", "hourUtc": 12, "station": "IODESS44", "solarRad": 420.4}, {"date": "2023-03-04", "hourUtc": 15, "station": "IODESS44", "solarRad": 36.8}, {"date": "2023-03-05", "hourUtc": 6, "station": "IODESS44", "solarRad": 79.8}, {"date": "2023-03-05", "hourUtc": 9, "station": "IODESS44", "solarRad": 309.3}, {"date": "2023-03-05", "hourUtc": 12, "station": "IODESS44", "solarRad": 420.7}, {"date": "2023-03-05", "hourUtc": 15, "station": "IODESS44", "solarRad": 41.6}, {"date": "2023-03-06", "hourUtc": 6, "station": "IODESS44", "solarRad": 42.5}, {"date": "2023-03-06", "hourUtc": 9, "station": "IODESS44", "solarRad": 543.0}, {"date": "2023-03-06", "hourUtc": 12, "station": "IODESS44", "solarRad": 106.7}, {"date": "2023-03-06", "hourUtc": 15, "station": "IODESS44", "solarRad": 25.6}, {"date": "2023-03-07", "hourUtc": 6, "station": "IODESS44", "solarRad": 98.8}, {"date": "2023-03-07", "hourUtc": 9, "station": "IODESS44", "solarRad": 273.3}, {"date": "2023-03-07", "hourUtc": 12, "station": "IODESS44", "solarRad": 524.5}, {"date": "2023-03-07", "hourUtc": 15, "station": "IODESS44", "solarRad": 44.7}, {"date": "2023-03-08", "hourUtc": 6, "station": "IODESS44", "solarRad": 85.4}, {"date": "2023-03-08", "hourUtc": 9, "station": "IODESS44", "solarRad": 518.3}, {"date": "2023-03-08", "hourUtc": 12, "station": "IODESS44", "solarRad": 331.8}, {"date": "2023-03-08", "hourUtc": 15, "station": "IODESS44", "solarRad": 59.3}, {"date": "2023-03-09", "hourUtc": 6, "station": "IODESS44", "solarRad": 127.5}, {"date": "2023-03-09", "hourUtc": 9, "station": "IODESS44", "solarRad": 294.5}, {"date": "2023-03-09", "hourUtc": 12, "station": "IODESS44", "solarRad": 429.4}, {"date": "2023-03-09", "hourUtc": 15, "station": "IODESS44", "solarRad": 54.2}, {"date": "2023-03-10", "hourUtc": 6, "station": "IODESS44", "solarRad": 85.9}, {"date": "2023-03-10", "hourUtc": 9, "station": "IODESS44", "solarRad": 552.2}, {"date": "2023-03-10", "hourUtc": 12, "station": "IODESS44", "solarRad": 424.6}, {"date": "2023-03-10", "hourUtc": 15, "station": "IODESS44", "solarRad": 54.2}, {"date": "2023-03-11", "hourUtc": 6, "station": "IODESS44", "solarRad": 97.5}, {"date": "2023-03-11", "hourUtc": 9, "station": "IODESS44", "solarRad": 348.8}, {"date": "2023-03-11", "hourUtc": 12, "station": "IODESS44", "solarRad": 90.7}, {"date": "2023-03-11", "hourUtc": 15, "station": "IODESS44", "solarRad": 24.2}, {"date": "2023-03-12", "hourUtc": 6, "station": "IODESS44", "solarRad": 135.3}, {"date": "2023-03-12", "hourUtc": 9, "station": "IODESS44", "solarRad": 757.9}, {"date": "2023-03-12", "hourUtc": 12, "station": "IODESS44", "solarRad": 579.1}, {"date": "2023-03-12", "hourUtc": 15, "station": "IODESS44", "solarRad": 68.0}, {"date": "2023-03-13", "hourUtc": 6, "station": "IODESS44", "solarRad": 121.4}, {"date": "2023-03-13", "hourUtc": 9, "station": "IODESS44", "solarRad": 570.5}, {"date": "2023-03-13", "hourUtc": 12, "station": "IODESS44", "solarRad": 490.2}, {"date": "2023-03-13", "hourUtc": 15, "station": "IODESS44", "solarRad": 63.7}, {"date": "2023-03-14", "hourUtc": 6, "station": "IODESS44", "solarRad": 122.3}, {"date": "2023-03-14", "hourUtc": 9, "station": "IODESS44", "solarRad": 583.9}, {"date": "2023-03-14", "hourUtc": 12, "station": "IODESS44", "solarRad": 462.8}, {"date": "2023-03-14", "hourUtc": 15, "station": "IODESS44", "solarRad": 67.2}, {"date": "2023-03-15", "hourUtc": 6, "station": "IODESS44", "solarRad": 170.4}, {"date": "2023-03-15", "hourUtc": 9, "station": "IODESS44", "solarRad": 199.0}, {"date": "2023-03-15", "hourUtc": 12, "station": "IODESS44", "solarRad": 100.2}, {"date": "2023-03-15", "hourUtc": 15, "station": "IODESS44", "solarRad": 25.6}, {"date": "2023-03-16", "hourUtc": 6, "station": "IODESS44", "solarRad": 45.0}, {"date": "2023-03-16", "hourUtc": 9, "station": "IODESS44", "solarRad": 171.3}, {"date": "2023-03-16", "hourUtc": 12, "station": "IODESS44", "solarRad": 156.1}, {"date": "2023-03-16", "hourUtc": 15, "station": "IODESS44", "solarRad": 28.6}, {"date": "2023-03-17", "hourUtc": 6, "station": "IODESS44", "solarRad": 89.3}, {"date": "2023-03-17", "hourUtc": 9, "station": "IODESS44", "solarRad": 295.3}, {"date": "2023-03-17", "hourUtc": 12, "station": "IODESS44", "solarRad": 306.2}, {"date": "2023-03-17", "hourUtc": 15, "station": "IODESS44", "solarRad": 16.9}, {"date": "2023-03-18", "hourUtc": 6, "station": "IODESS44", "solarRad": 28.1}, {"date": "2023-03-18", "hourUtc": 9, "station": "IODESS44", "solarRad": 159.2}, {"date": "2023-03-18", "hourUtc": 12, "station": "IODESS44", "solarRad": 181.3}, {"date": "2023-03-18", "hourUtc": 15, "station": "IODESS44", "solarRad": 28.6}, {"date": "2023-03-19", "hourUtc": 6, "station": "IODESS44", "solarRad": 55.9}, {"date": "2023-03-19", "hourUtc": 9, "station": "IODESS44", "solarRad": 164.3}, {"date": "2023-03-19", "hourUtc": 12, "station": "IODESS44", "solarRad": 213.8}, {"date": "2023-03-19", "hourUtc": 15, "station": "IODESS44", "solarRad": 19.5}, {"date": "2023-03-20", "hourUtc": 6, "station": "IODESS44", "solarRad": 144.4}, {"date": "2023-03-20", "hourUtc": 9, "station": "IODESS44", "solarRad": 589.0}, {"date": "2023-03-20", "hourUtc": 12, "station": "IODESS44", "solarRad": 460.2}, {"date": "2023-03-20", "hourUtc": 15, "station": "IODESS44", "solarRad": 73.3}, {"date": "2023-03-21", "hourUtc": 6, "station": "IODESS44", "solarRad": 96.7}, {"date": "2023-03-21", "hourUtc": 9, "station": "IODESS44", "solarRad": 446.3}, {"date": "2023-03-21", "hourUtc": 12, "station": "IODESS44", "solarRad": 180.4}, {"date": "2023-03-21", "hourUtc": 15, "station": "IODESS44", "solarRad": 62.9}, {"date": "2023-03-22", "hourUtc": 6, "station": "IODESS44", "solarRad": 149.1}, {"date": "2023-03-22", "hourUtc": 9, "station": "IODESS44", "solarRad": 501.5}, {"date": "2023-03-22", "hourUtc": 12, "station": "IODESS44", "solarRad": 331.4}, {"date": "2023-03-22", "hourUtc": 15, "station": "IODESS44", "solarRad": 83.7}, {"date": "2023-03-23", "hourUtc": 6, "station": "IODESS44", "solarRad": 186.9}, {"date": "2023-03-23", "hourUtc": 9, "station": "IODESS44", "solarRad": 572.2}, {"date": "2023-03-23", "hourUtc": 12, "station": "IODESS44", "solarRad": 512.7}, {"date": "2023-03-23", "hourUtc": 15, "station": "IODESS44", "solarRad": 93.2}, {"date": "2023-03-24", "hourUtc": 6, "station": "IODESS44", "solarRad": 228.5}, {"date": "2023-03-24", "hourUtc": 9, "station": "IODESS44", "solarRad": 662.0}, {"date": "2023-03-24", "hourUtc": 12, "station": "IODESS44", "solarRad": 530.5}, {"date": "2023-03-24", "hourUtc": 15, "station": "IODESS44", "solarRad": 60.2}, {"date": "2023-03-25", "hourUtc": 6, "station": "IODESS44", "solarRad": 92.4}, {"date": "2023-03-25", "hourUtc": 9, "station": "IODESS44", "solarRad": 296.2}, {"date": "2023-03-25", "hourUtc": 12, "station": "IODESS44", "solarRad": 226.4}, {"date": "2023-03-25", "hourUtc": 15, "station": "IODESS44", "solarRad": 28.1}, {"date": "2023-03-26", "hourUtc": 6, "station": "IODESS44", "solarRad": 53.7}, {"date": "2023-03-26", "hourUtc": 9, "station": "IODESS44", "solarRad": 76.3}, {"date": "2023-03-26", "hourUtc": 12, "station": "IODESS44", "solarRad": 399.9}, {"date": "2023-03-26", "hourUtc": 15, "station": "IODESS44", "solarRad": 11.6}, {"date": "2023-03-27", "hourUtc": 6, "station": "IODESS44", "solarRad": 219.8}, {"date": "2023-03-27", "hourUtc": 9, "station": "IODESS44", "solarRad": 572.5}, {"date": "2023-03-27", "hourUtc": 12, "station": "IODESS44", "solarRad": 527.0}, {"date": "2023-03-27", "hourUtc": 15, "station": "IODESS44", "solarRad": 66.3}, {"date": "2023-03-28", "hourUtc": 6, "station": "IODESS44", "solarRad": 35.1}, {"date": "2023-03-28", "hourUtc": 9, "station": "IODESS44", "solarRad": 400.8}, {"date": "2023-03-29", "hourUtc": 6, "station": "IODESS44", "solarRad": 237.7}, {"date": "2023-03-29", "hourUtc": 9, "station": "IODESS44", "solarRad": 843.3}, {"date": "2023-03-29", "hourUtc": 12, "station": "IODESS44", "solarRad": 230.2}, {"date": "2023-03-29", "hourUtc": 15, "station": "IODESS44", "solarRad": 71.1}, {"date": "2023-03-30", "hourUtc": 6, "station": "IODESS44", "solarRad": 211.1}, {"date": "2023-03-30", "hourUtc": 9, "station": "IODESS44", "solarRad": 739.6}, {"date": "2023-03-30", "hourUtc": 12, "station": "IODESS44", "solarRad": 525.3}, {"date": "2023-03-31", "hourUtc": 6, "station": "IODESS44", "solarRad": 212.5}, {"date": "2023-03-31", "hourUtc": 9, "station": "IODESS44", "solarRad": 376.9}, {"date": "2023-03-31", "hourUtc": 12, "station": "IODESS44", "solarRad": 346.1}, {"date": "2023-03-31", "hourUtc": 15, "station": "IODESS44", "solarRad": 101.1}]