[
  {
    "date": "2026-07-13",
    "T": {
      "min": 18.7,
      "max": 22.6,
      "app_min": 19.4,
      "app_max": 23.9,
      "night_mean": 19.7,
      "day_mean": 21.5
    },
    "Td_mean": 15.9,
    "RH_mean": 74.4,
    "vis_min": 24355.0,
    "precip_mm": 3.8,
    "precip_prob_max": 65.0,
    "snow_cm": 0.0,
    "weathercode_dom": 2.38,
    "pressure_mean": 1013.1,
    "wind": {
      "mean_kmh": 7.2,
      "max_kmh": 9.8,
      "gust_max_kmh": 18.6,
      "spd80": 11.2
    },
    "cloud": {
      "total": 74.5,
      "low": 19.7,
      "mid": 45.4,
      "high": 40.8,
      "c925": 4.2,
      "c850": 9.1,
      "c700": 32.4,
      "c500": 12.7,
      "c300": 7.4,
      "c10": 0.0
    },
    "conv": {
      "CAPE_max": 712.5,
      "CAPE_mean": 271.9,
      "LI_min": -1.2,
      "CIN": 16.4
    },
    "tp": {
      "T925": 16.5,
      "T850": 11.5,
      "T700": 1.3,
      "T600": -5.3,
      "T500": -14.2,
      "T400": -26.0,
      "T300": -40.0,
      "T250": -40.6,
      "T200": -41.4,
      "Td925": 11.2,
      "Td850": 7.7,
      "Td700": -0.8,
      "Td500": -20.1,
      "def850": 3.8,
      "def700": 2.1,
      "T50": -55.2,
      "T30": -50.9,
      "T10": -36.4
    },
    "gp": {
      "Z925": 782.3,
      "Z850": 1496.6,
      "Z700": 3090.0,
      "Z600": 4316.6,
      "Z500": 5724.7,
      "Z400": 7378.8,
      "Z300": 9398.1,
      "Z250": 10637.0,
      "Z200": 12156.3,
      "Z150": 14077.5,
      "Z100": 16686.0,
      "Z50": 21100.6,
      "Z30": 24387.3,
      "Z10": 31767.8
    },
    "rh": {
      "RH925": 71.9,
      "RH850": 78.2,
      "RH700": 86.3,
      "RH500": 64.1,
      "RH300": 49.9,
      "RH10": 0.0
    },
    "omega": {
      "W1000": -0.0,
      "W925": -0.0,
      "W850": -0.0,
      "W700": -0.0,
      "W600": -0.0,
      "W500": 0.0,
      "W400": 0.0,
      "W300": 0.0
    },
    "wp": {
      "925": {
        "s": 9.0,
        "d": 207.3
      },
      "850": {
        "s": 10.9,
        "d": 164.8
      },
      "700": {
        "s": 11.8,
        "d": 230.5
      },
      "500": {
        "s": 35.2,
        "d": 228.0
      },
      "300": {
        "s": 96.2,
        "d": 225.1
      },
      "250": {
        "s": 92.2,
        "d": 234.0
      },
      "200": {
        "s": 100.4,
        "d": 232.9
      },
      "100": {
        "s": 50.7,
        "d": 242.1
      },
      "50": {
        "s": 17.5,
        "d": 95.2
      },
      "10": {
        "s": 53.8,
        "d": 92.2
      }
    },
    "freeze_level_m": 3327.1
  },
  {
    "date": "2026-07-14",
    "T": {
      "min": 18.3,
      "max": 25.6,
      "app_min": 18.2,
      "app_max": 27.4,
      "night_mean": 20.0,
      "day_mean": 23.2
    },
    "Td_mean": 16.4,
    "RH_mean": 72.1,
    "vis_min": 23675.0,
    "precip_mm": 3.0,
    "precip_prob_max": 65.67,
    "snow_cm": 0.0,
    "weathercode_dom": 1.75,
    "pressure_mean": 1012.8,
    "wind": {
      "mean_kmh": 10.0,
      "max_kmh": 12.4,
      "gust_max_kmh": 22.5,
      "spd80": 15.2
    },
    "cloud": {
      "total": 71.9,
      "low": 14.0,
      "mid": 30.4,
      "high": 59.2,
      "c925": 2.1,
      "c850": 6.5,
      "c700": 17.0,
      "c500": 4.2,
      "c300": 16.7,
      "c10": 0.0
    },
    "conv": {
      "CAPE_max": 1002.5,
      "CAPE_mean": 478.2,
      "LI_min": -4.5,
      "CIN": 8.8
    },
    "tp": {
      "T925": 17.5,
      "T850": 12.6,
      "T700": 2.5,
      "T600": -4.6,
      "T500": -13.8,
      "T400": -25.7,
      "T300": -41.6,
      "T250": -46.2,
      "T200": -44.2,
      "Td925": 12.0,
      "Td850": 8.1,
      "Td700": -1.2,
      "Td500": -21.1,
      "def850": 4.5,
      "def700": 3.7,
      "T50": -54.5,
      "T30": -50.3,
      "T10": -37.1
    },
    "gp": {
      "Z925": 782.9,
      "Z850": 1500.1,
      "Z700": 3100.6,
      "Z600": 4331.8,
      "Z500": 5742.6,
      "Z400": 7398.9,
      "Z300": 9416.4,
      "Z250": 10635.5,
      "Z200": 12122.8,
      "Z150": 14041.5,
      "Z100": 16673.7,
      "Z50": 21096.8,
      "Z30": 24392.3,
      "Z10": 31778.5
    },
    "rh": {
      "RH925": 70.8,
      "RH850": 74.6,
      "RH700": 77.3,
      "RH500": 56.6,
      "RH300": 74.5,
      "RH10": 0.0
    },
    "omega": {
      "W1000": -0.0,
      "W925": 0.0,
      "W850": 0.0,
      "W700": -0.0,
      "W600": -0.0,
      "W500": -0.0,
      "W400": -0.0,
      "W300": -0.0
    },
    "wp": {
      "925": {
        "s": 9.2,
        "d": 277.1
      },
      "850": {
        "s": 5.0,
        "d": 236.6
      },
      "700": {
        "s": 12.9,
        "d": 146.0
      },
      "500": {
        "s": 19.8,
        "d": 57.6
      },
      "300": {
        "s": 25.1,
        "d": 50.3
      },
      "250": {
        "s": 11.6,
        "d": 60.0
      },
      "200": {
        "s": 28.3,
        "d": 240.5
      },
      "100": {
        "s": 40.0,
        "d": 234.8
      },
      "50": {
        "s": 18.3,
        "d": 109.4
      },
      "10": {
        "s": 48.5,
        "d": 92.9
      }
    },
    "freeze_level_m": 3569.4
  },
  {
    "date": "2026-07-15",
    "T": {
      "min": 19.8,
      "max": 29.2,
      "app_min": 20.8,
      "app_max": 30.6,
      "night_mean": 21.8,
      "day_mean": 26.2
    },
    "Td_mean": 17.6,
    "RH_mean": 67.9,
    "vis_min": 19715.0,
    "precip_mm": 0.2,
    "precip_prob_max": 23.67,
    "snow_cm": 0.0,
    "weathercode_dom": 0.62,
    "pressure_mean": 1014.6,
    "wind": {
      "mean_kmh": 10.6,
      "max_kmh": 12.5,
      "gust_max_kmh": 24.7,
      "spd80": 16.8
    },
    "cloud": {
      "total": 28.1,
      "low": 18.3,
      "mid": 6.7,
      "high": 7.0,
      "c925": 2.5,
      "c850": 6.9,
      "c700": 3.6,
      "c500": 0.2,
      "c300": 0.5,
      "c10": 0.0
    },
    "conv": {
      "CAPE_max": 763.8,
      "CAPE_mean": 589.0,
      "LI_min": -3.0,
      "CIN": 9.5
    },
    "tp": {
      "T925": 19.8,
      "T850": 14.1,
      "T700": 3.8,
      "T600": -2.6,
      "T500": -11.5,
      "T400": -23.8,
      "T300": -40.2,
      "T250": -50.0,
      "T200": -51.1,
      "Td925": 13.6,
      "Td850": 9.9,
      "Td700": -2.2,
      "Td500": -24.5,
      "def850": 4.2,
      "def700": 6.0,
      "T50": -54.1,
      "T30": -50.0,
      "T10": -38.2
    },
    "gp": {
      "Z925": 805.7,
      "Z850": 1527.9,
      "Z700": 3136.0,
      "Z600": 4373.7,
      "Z500": 5795.6,
      "Z400": 7465.6,
      "Z300": 9497.1,
      "Z250": 10713.9,
      "Z200": 12154.6,
      "Z150": 14044.5,
      "Z100": 16673.4,
      "Z50": 21103.0,
      "Z30": 24406.9,
      "Z10": 31773.3
    },
    "rh": {
      "RH925": 68.5,
      "RH850": 76.4,
      "RH700": 66.1,
      "RH500": 37.2,
      "RH300": 43.4,
      "RH10": 0.0
    },
    "omega": {
      "W1000": -0.0,
      "W925": 0.0,
      "W850": 0.0,
      "W700": -0.0,
      "W600": -0.0,
      "W500": -0.0,
      "W400": -0.0,
      "W300": -0.0
    },
    "wp": {
      "925": {
        "s": 2.3,
        "d": 220.9
      },
      "850": {
        "s": 3.5,
        "d": 137.2
      },
      "700": {
        "s": 14.1,
        "d": 261.5
      },
      "500": {
        "s": 26.2,
        "d": 312.1
      },
      "300": {
        "s": 30.4,
        "d": 311.8
      },
      "250": {
        "s": 36.7,
        "d": 326.2
      },
      "200": {
        "s": 33.2,
        "d": 298.5
      },
      "100": {
        "s": 29.5,
        "d": 251.2
      },
      "50": {
        "s": 16.4,
        "d": 98.9
      },
      "10": {
        "s": 46.1,
        "d": 83.9
      }
    },
    "freeze_level_m": 3851.4
  },
  {
    "date": "2026-07-16",
    "T": {
      "min": 21.2,
      "max": 30.3,
      "app_min": 22.5,
      "app_max": 31.9,
      "night_mean": 23.6,
      "day_mean": 27.6
    },
    "Td_mean": 16.7,
    "RH_mean": 58.5,
    "vis_min": 26080.0,
    "precip_mm": 0.1,
    "precip_prob_max": 12.67,
    "snow_cm": 0.0,
    "weathercode_dom": 0.5,
    "pressure_mean": 1015.4,
    "wind": {
      "mean_kmh": 8.8,
      "max_kmh": 10.3,
      "gust_max_kmh": 19.8,
      "spd80": 14.7
    },
    "cloud": {
      "total": 29.4,
      "low": 10.5,
      "mid": 13.6,
      "high": 9.0,
      "c925": 0.0,
      "c850": 1.6,
      "c700": 9.2,
      "c500": 0.3,
      "c300": 0.4,
      "c10": 0.0
    },
    "conv": {
      "CAPE_max": 761.2,
      "CAPE_mean": 485.1,
      "LI_min": -3.7,
      "CIN": 38.9
    },
    "tp": {
      "T925": 21.4,
      "T850": 15.0,
      "T700": 4.0,
      "T600": -2.1,
      "T500": -11.1,
      "T400": -23.5,
      "T300": -40.1,
      "T250": -49.5,
      "T200": -52.4,
      "Td925": 12.2,
      "Td850": 9.5,
      "Td700": -2.1,
      "Td500": -28.3,
      "def850": 5.5,
      "def700": 6.1,
      "T50": -54.5,
      "T30": -50.7,
      "T10": -38.7
    },
    "gp": {
      "Z925": 816.2,
      "Z850": 1541.2,
      "Z700": 3151.9,
      "Z600": 4390.6,
      "Z500": 5814.9,
      "Z400": 7486.7,
      "Z300": 9519.6,
      "Z250": 10737.5,
      "Z200": 12178.3,
      "Z150": 14052.9,
      "Z100": 16676.6,
      "Z50": 21101.6,
      "Z30": 24398.1,
      "Z10": 31736.4
    },
    "rh": {
      "RH925": 56.5,
      "RH850": 70.4,
      "RH700": 65.8,
      "RH500": 26.6,
      "RH300": 39.2,
      "RH10": 0.0
    },
    "omega": {
      "W1000": 0.0,
      "W925": 0.0,
      "W850": 0.0,
      "W700": -0.0,
      "W600": -0.0,
      "W500": -0.0,
      "W400": -0.0,
      "W300": -0.0
    },
    "wp": {
      "925": {
        "s": 8.9,
        "d": 141.1
      },
      "850": {
        "s": 4.8,
        "d": 102.9
      },
      "700": {
        "s": 17.6,
        "d": 285.1
      },
      "500": {
        "s": 13.3,
        "d": 251.2
      },
      "300": {
        "s": 13.9,
        "d": 229.5
      },
      "250": {
        "s": 7.1,
        "d": 240.8
      },
      "200": {
        "s": 6.4,
        "d": 289.1
      },
      "100": {
        "s": 21.2,
        "d": 279.4
      },
      "50": {
        "s": 14.6,
        "d": 81.3
      },
      "10": {
        "s": 48.6,
        "d": 83.8
      }
    },
    "freeze_level_m": 3994.6
  },
  {
    "date": "2026-07-17",
    "T": {
      "min": 22.3,
      "max": 29.8,
      "app_min": 23.0,
      "app_max": 31.4,
      "night_mean": 24.0,
      "day_mean": 27.5
    },
    "Td_mean": 15.9,
    "RH_mean": 54.8,
    "vis_min": 28605.0,
    "precip_mm": 0.5,
    "precip_prob_max": 13.0,
    "snow_cm": 0.0,
    "weathercode_dom": 7.12,
    "pressure_mean": 1014.0,
    "wind": {
      "mean_kmh": 8.7,
      "max_kmh": 10.9,
      "gust_max_kmh": 21.2,
      "spd80": 14.5
    },
    "cloud": {
      "total": 30.4,
      "low": 3.6,
      "mid": 19.6,
      "high": 3.8,
      "c925": 0.0,
      "c850": 1.1,
      "c700": 13.5,
      "c500": 0.8,
      "c300": 1.2,
      "c10": 0.0
    },
    "conv": {
      "CAPE_max": 345.0,
      "CAPE_mean": 193.1,
      "LI_min": -1.2,
      "CIN": 49.7
    },
    "tp": {
      "T925": 21.7,
      "T850": 15.4,
      "T700": 3.9,
      "T600": -1.6,
      "T500": -10.1,
      "T400": -22.1,
      "T300": -38.3,
      "T250": -47.7,
      "T200": -55.2,
      "Td925": 11.0,
      "Td850": 8.8,
      "Td700": -1.8,
      "Td500": -23.6,
      "def850": 6.6,
      "def700": 5.7,
      "T50": -55.1,
      "T30": -51.1,
      "T10": -38.0
    },
    "gp": {
      "Z925": 804.4,
      "Z850": 1530.1,
      "Z700": 3141.1,
      "Z600": 4380.6,
      "Z500": 5809.4,
      "Z400": 7489.7,
      "Z300": 9536.0,
      "Z250": 10763.7,
      "Z200": 12206.8,
      "Z150": 14057.1,
      "Z100": 16669.9,
      "Z50": 21081.6,
      "Z30": 24371.3,
      "Z10": 31706.2
    },
    "rh": {
      "RH925": 51.1,
      "RH850": 65.3,
      "RH700": 69.4,
      "RH500": 39.8,
      "RH300": 43.4,
      "RH10": 0.0
    },
    "omega": {
      "W1000": 0.0,
      "W925": 0.0,
      "W850": 0.0,
      "W700": -0.0,
      "W600": -0.0,
      "W500": -0.0,
      "W400": 0.0,
      "W300": -0.0
    },
    "wp": {
      "925": {
        "s": 12.7,
        "d": 124.4
      },
      "850": {
        "s": 12.4,
        "d": 161.5
      },
      "700": {
        "s": 16.5,
        "d": 251.8
      },
      "500": {
        "s": 16.7,
        "d": 221.6
      },
      "300": {
        "s": 22.1,
        "d": 180.0
      },
      "250": {
        "s": 21.0,
        "d": 176.2
      },
      "200": {
        "s": 15.3,
        "d": 190.2
      },
      "100": {
        "s": 24.7,
        "d": 295.0
      },
      "50": {
        "s": 11.5,
        "d": 80.5
      },
      "10": {
        "s": 49.9,
        "d": 90.4
      }
    },
    "freeze_level_m": 3971.1
  }
]