{
  "generated_at": "2026-06-04T17:44:00Z",
  "last_checked": "2026-06-04T17:44:00Z",
  "changed": true,
  "data_hash": "1d93400ad94e",
  "days_count": 5,
  "text": "## Сегодня, 4 июня\n\nНад Одессой установится слабое антициклональное поле с давлением 1013 гПа, но влияние моря сохранит высокую влажность в нижней тропосфере — точка росы у поверхности достигнет 14.8°C при относительной влажности 84%. Температурный фон умеренный: дневной максимум ограничится 18.8°C, ночью опустится до 15.9°C. Слабые восходящие движения на всех уровнях и минимальная конвективная энергия (CAPE едва дотянет до 72 Дж/кг, LI почти нейтрален на уровне -0.2) исключат развитие конвекции, хотя низкая облачность покроет до 35% неба. Западный перенос в средней тропосфере (до 24 км/ч на 500 гПа) обеспечит адвекцию сухого воздуха выше 700 гПа, но приземный слой останется влажным из-за морского влияния. Символические осадки в 0.2 мм с вероятностью до 19% не окажут практического влияния на погоду.\n\n## Завтра, 5 июня\n\nАнтициклон укрепится до 1015 гПа, что спровоцирует заметное прогревание — дневная температура подскочит до 21.3°C на фоне малооблачного неба (общая облачность сократится до 23%, низкая — до символических 5%). Дефицит точки росы в средней тропосфере увеличится: на уровне 850 гПа разрыв T-Td вырастет с 4.7°C до 7.2°C, что укажет на иссушение воздушной массы. Нулевая изотерма поднимется до 3598 метров, конвективный потенциал окончательно угаснет (CAPE 17 Дж/кг, LI положителен), осадков не предвидится. Ветровой режим останется слабым — приземные потоки не превысят 10 км/ч, в высотной тропосфере произойдёт перестройка циркуляции с западной на северо-западную с ослаблением струйных течений до 17 км/ч на 200 гПа.\n\n## Последующие 3 дня (6–8 июня)\n\nС 6 июня начнётся трансформация синоптической ситуации: давление продолжит рост до максимальных 1017 гПа к 7 числу, но одновременно высокая облачность верхнего яруса разрастётся до 73%, что укажет на приближение фронтальной зоны в средней тропосфере. К 7 июня влагосодержание резко возрастёт на всех уровнях — относительная влажность на 700 гПа подскочит с 54% до 84%, дефицит T-Td сократится до 2.6°C, а точка росы на 500 гПа поднимется с -24.9°C до -18.2°C. Это зарядит атмосферу конвективной неустойчивостью: CAPE взлетит до 397 Дж/кг (средние значения около 200 Дж/кг), индекс LI опустится до -0.8, что в сочетании с усилением юго-западного переноса (до 18 км/ч на 700 гПа) создаст предпосылки для развития ливневых процессов"
}