{
  "ECMWF IFS": [
    {
      "run_time": "2026-07-12T19:43:34Z",
      "detected_at": "2026-07-13T00:27:08Z"
    },
    {
      "run_time": "2026-07-13T01:05:37Z",
      "detected_at": "2026-07-13T01:09:16Z"
    }
  ],
  "ICON EU": [
    {
      "run_time": "2026-07-12T23:55:30Z",
      "detected_at": "2026-07-13T00:27:08Z"
    },
    {
      "run_time": "2026-07-13T03:39:44Z",
      "detected_at": "2026-07-13T03:54:14Z"
    },
    {
      "run_time": "2026-07-13T05:53:57Z",
      "detected_at": "2026-07-13T06:10:03Z"
    }
  ],
  "UKMO": [
    {
      "run_time": "2026-07-12T19:28:01Z",
      "detected_at": "2026-07-13T00:27:08Z"
    },
    {
      "run_time": "2026-07-13T01:11:13Z",
      "detected_at": "2026-07-13T01:24:58Z"
    },
    {
      "run_time": "2026-07-13T07:29:55Z",
      "detected_at": "2026-07-13T07:39:46Z"
    }
  ],
  "Arpège": [
    {
      "run_time": "2026-07-12T22:19:04Z",
      "detected_at": "2026-07-13T00:27:08Z"
    },
    {
      "run_time": "2026-07-13T03:38:01Z",
      "detected_at": "2026-07-13T03:39:43Z"
    }
  ],
  "GFS": [
    {
      "run_time": "2026-07-12T23:30:24Z",
      "detected_at": "2026-07-13T00:27:08Z"
    },
    {
      "run_time": "2026-07-13T05:29:41Z",
      "detected_at": "2026-07-13T05:38:41Z"
    }
  ],
  "GRAPES": [
    {
      "run_time": "2026-07-12T18:44:15Z",
      "detected_at": "2026-07-13T00:27:08Z"
    },
    {
      "run_time": "2026-07-13T00:31:08Z",
      "detected_at": "2026-07-13T00:38:49Z"
    },
    {
      "run_time": "2026-07-13T07:07:28Z",
      "detected_at": "2026-07-13T07:09:05Z"
    }
  ]
}