[
  {
    "label": "tiktok_1",
    "seed_video": "https://vt.tiktok.com/ZSXYQNS8T/",
    "channel_url": "https://www.tiktok.com/@MS4wLjABAAAAw-N19Dg1aDGRWeRNNnz5NERR56QIB8Xw_3n61J94KgTwrd3OrRwR1eFEbH4NHjbz",
    "last_playlist_debug": [
      {
        "id": "7663014476471405842",
        "timestamp": 1784184602,
        "upload_date": "20260716"
      },
      {
        "id": "7662997612957551879",
        "timestamp": 1784180673,
        "upload_date": "20260716"
      },
      {
        "id": "7662717632000298247",
        "timestamp": 1784115487,
        "upload_date": "20260715"
      },
      {
        "id": "7662636607299718408",
        "timestamp": 1784096625,
        "upload_date": "20260715"
      },
      {
        "id": "7662610840981556487",
        "timestamp": 1784090624,
        "upload_date": "20260715"
      }
    ],
    "last_run_diag": {
      "video_size": 19266132,
      "audio_size": 1195030,
      "n_frames": 12,
      "speech_len": 946,
      "ocr_len": 313,
      "probe": {
        "programs": [],
        "streams": [
          {
            "codec_name": "aac",
            "codec_type": "audio"
          },
          {
            "codec_name": "hevc",
            "codec_type": "video",
            "width": 1080,
            "height": 1920,
            "pix_fmt": "yuv420p"
          }
        ],
        "format": {
          "format_name": "mov,mp4,m4a,3gp,3g2,mj2",
          "duration": "74.581995",
          "size": "19266132"
        }
      },
      "speech_text_sample": " Гидроми центр курит в сторонке, когда я иду на замеры температуры воды в Черном море. И только у меня есть специальный прибор по замеру именно морской воды. Итак, друзья, замеряем. Обстановочку на пляже и что там ловится сегодня в Одессе? Смотрим с вами вместе. Водичка сегодня всякие прозрачные. Людей уже на пляже с утра много. Здорово. Смотрите, есть рыбаки у нас. Посмотрим, что там ловится в Одессе. Так, ребята, тут такой маленький бочок. Это наживка для ската. Но ребята говорят, что сегодня что-то его нет. Так, это у нас сарганчик такой. Сегодня ловится. Смотрите, пока вы спите, тут уже ло",
      "ocr_text_sample": "16.07.26\nЗамер Температуры\nМоря в Одессе\n\n16.07.26\nЗамер Температуры\nМоря в Одессе\n\n\nи.)\nв,\nШ\n=\n<\n®\n\nМоря в Одессе\n\nЗамер Температуры\n\n\n16.07.26\nЗамер Температуры\nМоря в Одессе\n\n\n16.07.26\nЗамер Температуры\nМоря в Одессе\n\n\n16.07.26\nЗамер Температуры\nМоря в Одессе\n\n\n16.07.26\nЗамер Температуры`\nМоря в Одессе\n\n\n\n\n\n\n"
    },
    "last_video_id": "7663014476471405842",
    "default_beach": "Ривьера"
  },
  {
    "label": "tiktok_2",
    "seed_video": "https://www.tiktok.com/@vyacheslav_tes",
    "channel_url": "https://www.tiktok.com/@vyacheslav_tes",
    "last_playlist_debug": [
      {
        "id": "7663032622485884168",
        "timestamp": 1784188824,
        "upload_date": "20260716"
      },
      {
        "id": "7662652123271679239",
        "timestamp": 1784100237,
        "upload_date": "20260715"
      },
      {
        "id": "7662284932303113480",
        "timestamp": 1784014751,
        "upload_date": "20260714"
      },
      {
        "id": "7661905581946539282",
        "timestamp": 1783926425,
        "upload_date": "20260713"
      },
      {
        "id": "7661536703114431752",
        "timestamp": 1783840528,
        "upload_date": "20260712"
      }
    ],
    "last_run_diag": {
      "video_size": 82288810,
      "audio_size": null,
      "n_frames": 12,
      "speech_len": 0,
      "ocr_len": 258,
      "probe": {
        "programs": [],
        "streams": [
          {
            "codec_name": "hevc",
            "codec_type": "video",
            "width": 1080,
            "height": 1920,
            "pix_fmt": "yuv420p"
          }
        ],
        "format": {
          "format_name": "mov,mp4,m4a,3gp,3g2,mj2",
          "duration": "203.650000",
          "size": "82288810"
        }
      },
      "speech_error": "ffmpeg exit=234:     minor_version   : 512\n    compatible_brands: isomiso2mp41iso5\n    aigc_info       : {\"aigc_label_type\":0}\n    comment         : vid:v1c044g50000d9c8rsvog65g6okt3opg\n    vid_md5         : 37f7069cc75465ef87a7cfe26afbcc27\n    encoder         : Lavf58.76.100\n  Duration: 00:03:23.65, start: 0.000000, bitrate: 3232 kb/s\n  Stream #0:0[0x2](und): Video: hevc (Main) (hvc1 / 0x31637668), yuv420p(tv, bt709), 1080x1920, 63 kb/s, SAR 1:1 DAR 9:16, 60 fps, 60 tbr, 15360 tbn (default)\n    Metadata:\n      handler_name    : Bento4 Video Handler\n      vendor_id       : [0][0][0][0]\nOutput #0, mp3, to '/tmp/tmpi3ts0s6w/audio.mp3':\n[out#0/mp3 @ 0x560f35f85ac0] Output file does not contain any stream\nError opening output file /tmp/tmpi3ts0s6w/audio.mp3.\nError opening output files: Invalid",
      "ocr_text_sample": "—°ё Я\n\n> вы А ркадия\n\nх ПУ ° че.\nЦ ВОДЫ ВМО ре\nЧАИ\n\n-\nг С\n\n\n| (0) > ь \\ ркадия\n\nАЕ\n\nЦ ВОВ ВМО ре ия\nАГ\n\n\nЕ\n>\nя\n5\nо\n©\n©\n\n\nтие ее ©\nэ> я я = - И\n\n\n[=] [1\nЯ 8\nИН ОИ |=\n\n4Л^44 э9\n\n[=]\n\nЯ ИЯ\nЕ.\n\n< 414 =э9\n\nу!\nй 1 № 9 “К й\nА\n\n\nэоз\n\nм]\nМАПТАЛЯИ\n\nь\n\n\n\n\nАо\n\nь 3\nча\n\n\n"
    },
    "last_error": "latest_video_info: ERROR: [TikTok] 7661536703114431752: Unexpected response from webpage request; please report this issue on  https://github.com/yt-dlp/yt-dlp/issues?q= , filling out the appropriate issue template. Confirm you are on the latest version using  yt-dlp -U\n",
    "last_skipped_reason": "no temp/date parsed (вероятно нерелевантный ролик)",
    "last_video_id": "7663032622485884168"
  },
  {
    "label": "tiktok_3",
    "seed_video": "https://www.tiktok.com/@katsea_ua",
    "channel_url": "https://www.tiktok.com/@katsea_ua",
    "last_playlist_debug": [
      {
        "id": "7663033998465092896",
        "timestamp": 1784189144,
        "upload_date": "20260716"
      },
      {
        "id": "7662636215681797409",
        "timestamp": 1784096539,
        "upload_date": "20260715"
      },
      {
        "id": "7662593125243833633",
        "timestamp": 1784086526,
        "upload_date": "20260715"
      },
      {
        "id": "7662455133367815457",
        "timestamp": 1784054364,
        "upload_date": "20260714"
      },
      {
        "id": "7662246037683326241",
        "timestamp": 1784005692,
        "upload_date": "20260714"
      }
    ],
    "last_run_diag": {
      "video_size": 15008382,
      "audio_size": 1047076,
      "n_frames": 12,
      "speech_len": 481,
      "ocr_len": 14,
      "probe": {
        "programs": [],
        "streams": [
          {
            "codec_name": "aac",
            "codec_type": "audio"
          },
          {
            "codec_name": "h264",
            "codec_type": "video",
            "width": 576,
            "height": 1024,
            "pix_fmt": "yuv420p"
          }
        ],
        "format": {
          "format_name": "mov,mp4,m4a,3gp,3g2,mj2",
          "duration": "65.339002",
          "size": "15008382"
        }
      },
      "speech_text_sample": " Одесса 16 июля 2026 года. Делаем замер температуры воды в Черном море. Посмотрите, какая водичка. Вообще просто вымечает она прозрачная. Есть немного водорослей. Лепо! Вот так, кое-где. Попробивала полный пляж людей. Впереди, не надо. Люди купаются. Это уже 16 июля. Время сейчас 11.00. Температура выпуска 26 градусов. Сейчас посмотрим, что у нас температура воды. Вот полностью какая-то все. Красота такая. Парни, что? Температура воды на сегодня 22 градуса. Двадцать готой пас.",
      "ocr_text_sample": "\n\n\n\n\n\nр\n\n\n\n\n\n\n"
    },
    "last_video_id": "7663033998465092896"
  }
]