{
  "2026-06-20_evening": {
    "forecast": {
      "T_min": 22.8,
      "T_max": 27.7,
      "wind_mean": 1.9,
      "wind_max": 2.1,
      "gust_max": 4.8,
      "pressure_mean": 1020.4,
      "precip_mm": 0.2,
      "weathercode": 1.25
    },
    "fact": {
      "T_min": 24.8,
      "T_max": 27.3,
      "wind_mean": 2.0,
      "wind_max": 2,
      "pressure_mean": 1020.0,
      "precip_mm": 0.0,
      "had_rain": false,
      "had_thunder": false
    }
  },
  "2026-06-21_night": {
    "forecast": {
      "T_min": 20.9,
      "T_max": 22.8,
      "wind_mean": 2.7,
      "wind_max": 3.1,
      "gust_max": 5.3,
      "pressure_mean": 1021.5,
      "precip_mm": 0.0,
      "weathercode": 1.71
    },
    "fact": {
      "T_min": 21.6,
      "T_max": 22.6,
      "wind_mean": 0.5,
      "wind_max": 1,
      "pressure_mean": 1021.6,
      "precip_mm": 0.0,
      "had_rain": false,
      "had_thunder": false
    }
  },
  "2026-06-21_morning": {
    "forecast": {
      "T_min": 20.2,
      "T_max": 25.9,
      "wind_mean": 3.4,
      "wind_max": 3.5,
      "gust_max": 6.3,
      "pressure_mean": 1022.3,
      "precip_mm": 0.0,
      "weathercode": 1.0
    },
    "fact": {
      "T_min": 19.8,
      "T_max": 24.9,
      "wind_mean": 1.0,
      "wind_max": 1,
      "pressure_mean": 1022.0,
      "precip_mm": 0.0,
      "had_rain": false,
      "had_thunder": false
    }
  }
}